gitcomic/__init__.py
gitcomic/gitcomic.py
gitcomic_vieitesss-0.0.1.dist-info/METADATA
gitcomic_vieitesss-0.0.1.dist-info/WHEEL
gitcomic_vieitesss-0.0.1.dist-info/top_level.txt
gitcomic_vieitesss-0.0.1.dist-info/RECORD
