Metadata-Version: 2.1
Name: gitcomic-vieitesss
Version: 0.0.1
Summary: An app that allows you to create git commits including icons depending on the changes you have made in your repo.
Home-page: https://github.com/vieitesss/GitComic.git
Author: Daniel Vieites
Author-email: dvieitest@gmail.com
Project-URL: Bug Tracker, https://github.com/vieitesss/GitComic/issues
Classifier: Programming Language :: Python :: 3
Classifier: License :: OSI Approved :: MIT License
Classifier: Operating System :: OS Independent
Requires-Python: >=3.6
